pgsaw/Item.py
pgsaw/ItemNotFound.py
pgsaw/Store.py
pgsaw/StoreNotFound.py
pgsaw/UPC.py
pgsaw/UPCType.py
pgsaw/__init__.py
pgsaw/store/Caseys.py
pgsaw/store/Kwik.py
pgsaw/store/__init__.py
pgsaw-1.0.4.dist-info/LICENSE.md
pgsaw-1.0.4.dist-info/METADATA
pgsaw-1.0.4.dist-info/WHEEL
pgsaw-1.0.4.dist-info/top_level.txt
pgsaw-1.0.4.dist-info/RECORD
