Metadata-Version: 2.1
Name: pgsaw
Version: 1.0.4
Summary: Python Grocery Store API Wrapper
Home-page: https://github.com/b0bcarlson/pgsaw
Author: bobcodes
Author-email: pypi@bobcodes.net
License: UNKNOWN
Project-URL: Bug Tracker, https://github.com/b0bcarlson/pgsaw/issues
Platform: UNKNOWN
Classifier: Programming Language :: Python :: 3
Classifier: License :: OSI Approved :: GNU General Public License v3 (GPLv3)
Requires-Python: >=3.6
License-File: LICENSE.md
Requires-Dist: requests
Requires-Dist: beautifulsoup4
